hm/__init__.py
hm/config.py
hm/log.py
hm/storage.py
hm/iaas/__init__.py
hm/iaas/cloudstack_client.py
hm/lb_managers/__init__.py
hm/lb_managers/cloudstack.py
hm/lb_managers/elb.py
hm/lb_managers/networkapi_cloudstack.py
hm/managers/__init__.py
hm/managers/cloudstack.py
hm/managers/ec2.py
hm/model/__init__.py
hm/model/host.py
hm/model/load_balancer.py
tests/lb_managers/__init__.py
tests/lb_managers/test_cloudstack.py
tests/lb_managers/test_networkapi_cloudstack.py
tests/managers/__init__.py
tests/managers/test_base_manager.py
tests/managers/test_cloudstack_manager.py
tests/model/__init__.py
tests/model/test_host.py
tests/model/test_load_balancer.py
tsuru_hm-0.6.18.dist-info/LICENSE
tsuru_hm-0.6.18.dist-info/METADATA
tsuru_hm-0.6.18.dist-info/WHEEL
tsuru_hm-0.6.18.dist-info/top_level.txt
tsuru_hm-0.6.18.dist-info/RECORD
