Metadata-Version: 2.1
Name: tsuru-hm
Version: 0.6.18
Summary: Host manager library for tsuru PaaS services
Home-page: https://github.com/tsuru/hm
Author: Tsuru
Author-email: tsuru@corp.globo.com
License: UNKNOWN
Platform: UNKNOWN
Classifier: Programming Language :: Python :: 2.7
Requires-Dist: boto (==2.25.0)
Requires-Dist: pymongo (==3.3.0)
Requires-Dist: requests (==2.4.3)
Requires-Dist: GloboNetworkAPI (==0.2.2)
Provides-Extra: tests
Requires-Dist: mock (==2.0.0) ; extra == 'tests'
Requires-Dist: flake8 (==2.1.0) ; extra == 'tests'
Requires-Dist: coverage (==3.7.1) ; extra == 'tests'
Requires-Dist: freezegun (==0.2.8) ; extra == 'tests'
